mypackage/__init__.py
mypackage/topsis.py
topsis_sirish_ucs633-1.1.1.dist-info/LICENSE.lic
topsis_sirish_ucs633-1.1.1.dist-info/METADATA
topsis_sirish_ucs633-1.1.1.dist-info/WHEEL
topsis_sirish_ucs633-1.1.1.dist-info/entry_points.txt
topsis_sirish_ucs633-1.1.1.dist-info/top_level.txt
topsis_sirish_ucs633-1.1.1.dist-info/RECORD
