Metadata-Version: 2.1
Name: topsis-sirish-ucs633
Version: 1.1.1
Summary: A python package to implement topsis(MCDM)
Home-page: https://github.com/sirishbhu/topsis
Author: Sirish Bhuolia
Author-email: sirishbhudolia88@gmail.com
License: UNKNOWN
Platform: UNKNOWN
Classifier: Programming Language :: Python :: 3
Classifier: Programming Language :: Python :: 3.7
Classifier: License :: OSI Approved :: MIT License
Classifier: Operating System :: OS Independent
Requires-Python: >=3.6
